nbdev_1/__init__.py
nbdev_1/_modidx.py
nbdev_1/core.py
nbdev_1/foo.py
nbdev_test/__init__.py
nbdev_test/_modidx.py
nbdev_test/foo.py
pixel.nbdev.test-0.0.1.dist-info/LICENSE
pixel.nbdev.test-0.0.1.dist-info/METADATA
pixel.nbdev.test-0.0.1.dist-info/WHEEL
pixel.nbdev.test-0.0.1.dist-info/entry_points.txt
pixel.nbdev.test-0.0.1.dist-info/top_level.txt
pixel.nbdev.test-0.0.1.dist-info/RECORD
